qiskit_experiments/VERSION.txt
qiskit_experiments/__init__.py
qiskit_experiments/exceptions.py
qiskit_experiments/version.py
qiskit_experiments/curve_analysis/__init__.py
qiskit_experiments/curve_analysis/base_curve_analysis.py
qiskit_experiments/curve_analysis/composite_curve_analysis.py
qiskit_experiments/curve_analysis/curve_analysis.py
qiskit_experiments/curve_analysis/curve_data.py
qiskit_experiments/curve_analysis/fit_function.py
qiskit_experiments/curve_analysis/guess.py
qiskit_experiments/curve_analysis/scatter_table.py
qiskit_experiments/curve_analysis/utils.py
qiskit_experiments/curve_analysis/standard_analysis/__init__.py
qiskit_experiments/curve_analysis/standard_analysis/bloch_trajectory.py
qiskit_experiments/curve_analysis/standard_analysis/decay.py
qiskit_experiments/curve_analysis/standard_analysis/error_amplification_analysis.py
qiskit_experiments/curve_analysis/standard_analysis/gaussian.py
qiskit_experiments/curve_analysis/standard_analysis/oscillation.py
qiskit_experiments/data_processing/__init__.py
qiskit_experiments/data_processing/data_action.py
qiskit_experiments/data_processing/data_processor.py
qiskit_experiments/data_processing/discriminator.py
qiskit_experiments/data_processing/exceptions.py
qiskit_experiments/data_processing/nodes.py
qiskit_experiments/data_processing/processor_library.py
qiskit_experiments/data_processing/sklearn_discriminators.py
qiskit_experiments/data_processing/mitigation/__init__.py
qiskit_experiments/data_processing/mitigation/base_readout_mitigator.py
qiskit_experiments/data_processing/mitigation/correlated_readout_mitigator.py
qiskit_experiments/data_processing/mitigation/local_readout_mitigator.py
qiskit_experiments/data_processing/mitigation/utils.py
qiskit_experiments/database_service/__init__.py
qiskit_experiments/database_service/device_component.py
qiskit_experiments/database_service/exceptions.py
qiskit_experiments/database_service/utils.py
qiskit_experiments/framework/__init__.py
qiskit_experiments-0.12.0.dist-info/licenses/LICENSE.txt
qiskit_experiments-0.12.0.dist-info/METADATA
qiskit_experiments-0.12.0.dist-info/WHEEL
qiskit_experiments-0.12.0.dist-info/entry_points.txt
qiskit_experiments-0.12.0.dist-info/top_level.txt
qiskit_experiments-0.12.0.dist-info/RECORD
