Metadata-Version: 2.4
Name: qiskit-experiments
Version: 0.12.0
Summary: Software for developing quantum computing programs
Author-email: Qiskit Development Team <qiskit@us.ibm.com>
License: Apache 2.0
Project-URL: Homepage, https://github.com/Qiskit-Community/qiskit-experiments
Project-URL: Bug Tracker, https://github.com/Qiskit-Community/qiskit-experiments/issues
Project-URL: Documentation, https://qiskit-community.github.io/qiskit-experiments
Project-URL: Source Code, https://github.com/Qiskit-Community/qiskit-experiments
Keywords: qiskit sdk quantum
Classifier: Environment :: Console
Classifier: Intended Audience :: Developers
Classifier: Intended Audience :: Science/Research
Classifier: License :: OSI Approved :: Apache Software License
Classifier: Operating System :: MacOS
Classifier: Operating System :: Microsoft :: Windows
Classifier: Operating System :: POSIX :: Linux
Classifier: Programming Language :: Python :: 3 :: Only
Classifier: Programming Language :: Python :: 3.10
Classifier: Programming Language :: Python :: 3.11
Classifier: Programming Language :: Python :: 3.12
Classifier: Programming Language :: Python :: 3.13
Classifier: Programming Language :: Python :: 3.9
Classifier: Topic :: Scientific/Engineering
Requires-Python: >=3.9
License-File: LICENSE.txt
Requires-Dist: numpy>=1.17
Requires-Dist: scipy>=1.4
Requires-Dist: qiskit>=1.3
Requires-Dist: qiskit-ibm-experiment>=0.4.6
Requires-Dist: qiskit_ibm_runtime>=0.34.0
Requires-Dist: matplotlib>=3.4
Requires-Dist: uncertainties
Requires-Dist: lmfit
Requires-Dist: rustworkx
Requires-Dist: pandas>=1.1.5
Requires-Dist: packaging
Provides-Extra: extras
Requires-Dist: cvxpy>=1.3.2; extra == "extras"
Requires-Dist: scikit-learn; extra == "extras"
Requires-Dist: qiskit-aer>=0.13.2; extra == "extras"
Dynamic: license-file
